{
  "$schema": "https://raw.githubusercontent.com/dineug/erd-editor/main/json-schema/schema.json",
  "version": "3.0.0",
  "settings": {
    "width": 2000,
    "height": 2000,
    "scrollTop": -601.9229,
    "scrollLeft": -388.6751,
    "zoomLevel": 0.32,
    "show": 431,
    "database": 4,
    "databaseName": "",
    "canvasType": "ERD",
    "language": 1,
    "tableNameCase": 4,
    "columnNameCase": 2,
    "bracketType": 1,
    "relationshipDataTypeSync": true,
    "relationshipOptimization": false,
    "columnOrder": [
      1,
      2,
      4,
      8,
      16,
      32,
      64
    ],
    "maxWidthComment": -1,
    "ignoreSaveSettings": 0
  },
  "doc": {
    "tableIds": [
      "bJ7AOC6b5UBri3XKxWYJY",
      "3APtNOasTm-e0OA6a9FNY",
      "DsMm1UbPEc01xHb0e5kDp",
      "_B8cZ5qmp5gvIdren79eJ",
      "t-nhS9VuC9Mb4hcV-9Yt2",
      "cBh8ORWDjyegNE57Iuv2o",
      "9Ran1wBWSEnygQOVVznXd",
      "sl59DqkQiHdpea1EMLv-R",
      "pHxvDRevJXyNO9omgJdtS",
      "CKd0J5jyyS6BkdxLBP2mH",
      "ZZqHZvyPEOG31dM5HyoMZ",
      "PDSBscIUbI3lLRWMvjKsV"
    ],
    "relationshipIds": [
      "QtRMVYtBxuDPORMh0mBdp",
      "SriMF4zE240RWndT0irJG",
      "CYkOLGQC2RjCafAVkzS74",
      "vk1vQvEWh4J0BeYfNwOv1",
      "G7h1ObFI-S6KhWcTX7jS-",
      "gWU06k4oyCHZ-Rpixvm8g",
      "XNxtgQ3rgOa9Ae9Syk3h0",
      "yzRRJ6yZITA_lt7BBymsy",
      "TEWzEHRSevKxakZu3lXj1",
      "j0ZsCNqoafOo1I4ldlHFG",
      "X2ZX_2ydFjT7ZdCCEqSSm",
      "mRfRmX0y4MMhjZHM5yUmO",
      "LAwlFOnKcF9LL3AMzW0e2",
      "bMC1SpSxdfX8ZeNoEsXoZ",
      "dCVsjZpSGvLLULXUjSTJC"
    ],
    "indexIds": [
      "na_XlrGLWOGN3dNRrJQzz"
    ],
    "memoIds": [
      "2LAcKljObBZY5iIZKcr4a",
      "Bl6KcNpFmT3_BBgmrssNI",
      "9xNAZAvfZx1XCnUfsoWPo",
      "tsO7A6ZhrKp7ukdtr2z-e",
      "KCkfC8SPr6upozfYdxDF8"
    ]
  },
  "collections": {
    "tableEntities": {
      "bJ7AOC6b5UBri3XKxWYJY": {
        "id": "bJ7AOC6b5UBri3XKxWYJY",
        "name": "users",
        "comment": "서비스 사용자",
        "columnIds": [
          "Y5sg76HQD1b4WUYJJ4V9G",
          "qelqDKuxvmS8XcL1dHBDd",
          "ZYNf3lizgpnCOehkqkNnV",
          "JLymQu7fjq50FAAQE8qf9",
          "9gFNL8CfIs6lwKrGWB4E3",
          "38Djba51KwYs2dMmjf8Ap",
          "tXY5I8Nxdkkx4I9-pIjyE",
          "aJZyAWdElcgJ1lktVMOgu"
        ],
        "seqColumnIds": [
          "12bIRpyyz6SYpal4thnLn",
          "Y5sg76HQD1b4WUYJJ4V9G",
          "qelqDKuxvmS8XcL1dHBDd",
          "ZYNf3lizgpnCOehkqkNnV",
          "JLymQu7fjq50FAAQE8qf9",
          "9gFNL8CfIs6lwKrGWB4E3",
          "38Djba51KwYs2dMmjf8Ap",
          "tXY5I8Nxdkkx4I9-pIjyE",
          "aJZyAWdElcgJ1lktVMOgu"
        ],
        "ui": {
          "x": 34.9894,
          "y": 382.5131,
          "zIndex": 2,
          "widthName": 60,
          "widthComment": 68,
          "color": ""
        },
        "meta": {
          "updateAt": 1769593969348,
          "createAt": 1769438864626
        }
      },
      "BXUE3JL8xKO1yHghR6EJP": {
        "id": "BXUE3JL8xKO1yHghR6EJP",
        "name": "",
        "comment": "",
        "columnIds": [],
        "seqColumnIds": [],
        "ui": {
          "x": 453.2096,
          "y": 375.8986,
          "zIndex": 44,
          "widthName": 60,
          "widthComment": 60,
          "color": ""
        },
        "meta": {
          "updateAt": 1769510662805,
          "createAt": 1769510660631
        }
      },
      "lb1eOqXxrsRWi63DCNH6A": {
        "id": "lb1eOqXxrsRWi63DCNH6A",
        "name": "packs",
        "comment": "",
        "columnIds": [],
        "seqColumnIds": [],
        "ui": {
          "x": 177.8671,
          "y": 408.0729,
          "zIndex": 53,
          "widthName": 60,
          "widthComment": 60,
          "color": ""
        },
        "meta": {
          "updateAt": 1769512873036,
          "createAt": 1769511328822
        }
      },
      "3APtNOasTm-e0OA6a9FNY": {
        "id": "3APtNOasTm-e0OA6a9FNY",
        "name": "interest_categories",
        "comment": "취향 카테고리",
        "columnIds": [
          "Yik8C7n_4LANoofIXLQeJ",
          "_3UvUG5U39AngHYBHTyhJ",
          "toy7Kr3_W9WcaPYxsHChV"
        ],
        "seqColumnIds": [
          "23yFW8CX4fDCJD-2RV-8-",
          "Yik8C7n_4LANoofIXLQeJ",
          "2xZju6Dp2JIgXIVCgxpLK",
          "L8q3tzdncz7rxAHTHYpq5",
          "EsISW6Mr9DXlP36DBwsJF",
          "RloSc9qIoi_5JuwqEyJJb",
          "_kFZ7ZkPhzn-uJ98MLKU_",
          "iAvvIQF3trv6BKYOTp2SI",
          "_3UvUG5U39AngHYBHTyhJ",
          "toy7Kr3_W9WcaPYxsHChV"
        ],
        "ui": {
          "x": 1489.5813,
          "y": 218.9683,
          "zIndex": 62,
          "widthName": 111,
          "widthComment": 68,
          "color": ""
        },
        "meta": {
          "updateAt": 1769744517443,
          "createAt": 1769512876904
        }
      },
      "DsMm1UbPEc01xHb0e5kDp": {
        "id": "DsMm1UbPEc01xHb0e5kDp",
        "name": "situation_categories",
        "comment": "순간 카테고리",
        "columnIds": [
          "ZGvFOIXwQ1aP1SQKQ4I5i",
          "zDM1dgenIeHjC7RxZnb8J",
          "PZIhkKWR3s2Ys-lAC7NAr"
        ],
        "seqColumnIds": [
          "ZGvFOIXwQ1aP1SQKQ4I5i",
          "zDM1dgenIeHjC7RxZnb8J",
          "PZIhkKWR3s2Ys-lAC7NAr",
          "wPhAZPRRzNTTLn5Gr7CNt"
        ],
        "ui": {
          "x": 1536.7253,
          "y": 436.2867,
          "zIndex": 92,
          "widthName": 117,
          "widthComment": 68,
          "color": ""
        },
        "meta": {
          "updateAt": 1769744563427,
          "createAt": 1769513016056
        }
      },
      "_B8cZ5qmp5gvIdren79eJ": {
        "id": "_B8cZ5qmp5gvIdren79eJ",
        "name": "user_interest_categories",
        "comment": "사용자의 취향 카테고리",
        "columnIds": [
          "ZcBlR_Wxtb0eX2onfhMVR",
          "jgbj5Ow5Oi__-xi8rXagR",
          "dBb5AGYLM8jVGJeQwkprV"
        ],
        "seqColumnIds": [
          "ZcBlR_Wxtb0eX2onfhMVR",
          "jgbj5Ow5Oi__-xi8rXagR",
          "dBb5AGYLM8jVGJeQwkprV"
        ],
        "ui": {
          "x": 677.6251,
          "y": 207.7419,
          "zIndex": 126,
          "widthName": 142,
          "widthComment": 113,
          "color": ""
        },
        "meta": {
          "updateAt": 1769570069130,
          "createAt": 1769513148018
        }
      },
      "t-nhS9VuC9Mb4hcV-9Yt2": {
        "id": "t-nhS9VuC9Mb4hcV-9Yt2",
        "name": "user_situation_categories",
        "comment": "사용자의 순간 카테고리",
        "columnIds": [
          "-6nKsN3M0PV49ZxBTkPGI",
          "zc6g-Z520uRGElgQm_DuH",
          "uitMLZ80N_hGuoxqW-LEX"
        ],
        "seqColumnIds": [
          "-6nKsN3M0PV49ZxBTkPGI",
          "4h8DnXWfcsrFOMYoCcyGC",
          "zc6g-Z520uRGElgQm_DuH",
          "uitMLZ80N_hGuoxqW-LEX"
        ],
        "ui": {
          "x": 679.3185,
          "y": 418.5019,
          "zIndex": 143,
          "widthName": 148,
          "widthComment": 113,
          "color": ""
        },
        "meta": {
          "updateAt": 1769570065809,
          "createAt": 1769513231057
        }
      },
      "cBh8ORWDjyegNE57Iuv2o": {
        "id": "cBh8ORWDjyegNE57Iuv2o",
        "name": "packs",
        "comment": "사용자 생성 팩",
        "columnIds": [
          "SecDLSP7hc7TMIxoGvMON",
          "Lf-H19PaEikcDbGd-xXV4",
          "Jg9GfYS1ed0Xp9u9lhhoT",
          "cJr6u7X83snnYU136IQS1",
          "o_msB0MbTGb2uhC3SrOJP"
        ],
        "seqColumnIds": [
          "SecDLSP7hc7TMIxoGvMON",
          "q4XsS4TgYBxoL-nuye3fo",
          "Lf-H19PaEikcDbGd-xXV4",
          "KxA9qeagDOFxgyEA_Ma6i",
          "TEr5ElEuN_yR4rXy7aTg4",
          "Jg9GfYS1ed0Xp9u9lhhoT",
          "cJr6u7X83snnYU136IQS1",
          "o_msB0MbTGb2uhC3SrOJP",
          "Y_atxh8Yf_vJGL9u0Vysg"
        ],
        "ui": {
          "x": 1002.5852,
          "y": 611.0625,
          "zIndex": 207,
          "widthName": 60,
          "widthComment": 71,
          "color": ""
        },
        "meta": {
          "updateAt": 1769744586907,
          "createAt": 1769513747258
        }
      },
      "qGNzk1VxwkfSKRvH8KQ8O": {
        "id": "qGNzk1VxwkfSKRvH8KQ8O",
        "name": "interest_details",
        "comment": "취향 세부사항",
        "columnIds": [
          "nqZpfXMdmHOsL6RbUUM2f",
          "6fqObkZvz22PfHUOndUjb",
          "x4ZDUtpwRvpMn5Jqa3TJY"
        ],
        "seqColumnIds": [
          "nqZpfXMdmHOsL6RbUUM2f",
          "6fqObkZvz22PfHUOndUjb",
          "x4ZDUtpwRvpMn5Jqa3TJY"
        ],
        "ui": {
          "x": 1531.591,
          "y": 809.5057,
          "zIndex": 226,
          "widthName": 89,
          "widthComment": 68,
          "color": ""
        },
        "meta": {
          "updateAt": 1769570611746,
          "createAt": 1769514579876
        }
      },
      "YqpgNdCUwXpWWFYMZkHj0": {
        "id": "YqpgNdCUwXpWWFYMZkHj0",
        "name": "situation_details",
        "comment": "순간 세부사항",
        "columnIds": [
          "Ictq5yX_96r7zLmYbT9MC",
          "bP5dLdS8N3D_0oczoMX8e",
          "rREWLc4BJCj_zo6K1zQz4"
        ],
        "seqColumnIds": [
          "Ictq5yX_96r7zLmYbT9MC",
          "CPB3G6oYATPVAK4cDCk-Z",
          "bP5dLdS8N3D_0oczoMX8e",
          "rREWLc4BJCj_zo6K1zQz4"
        ],
        "ui": {
          "x": 1255.8098,
          "y": 645.2561,
          "zIndex": 249,
          "widthName": 95,
          "widthComment": 68,
          "color": ""
        },
        "meta": {
          "updateAt": 1769570597356,
          "createAt": 1769514673124
        }
      },
      "9Ran1wBWSEnygQOVVznXd": {
        "id": "9Ran1wBWSEnygQOVVznXd",
        "name": "item_images",
        "comment": "아이템 이미지",
        "columnIds": [
          "7FK0ufqsPBeAHm8jVTLKL",
          "3bjIvqWdn__100c0zx3xo",
          "i8Y6uANHTxdv3eWHTg1rP"
        ],
        "seqColumnIds": [
          "WhhmSvzblAHFpDIpavKae",
          "7FK0ufqsPBeAHm8jVTLKL",
          "2w5ryMWNqG2Eqg6gJwZN9",
          "3bjIvqWdn__100c0zx3xo",
          "i8Y6uANHTxdv3eWHTg1rP"
        ],
        "ui": {
          "x": 1406.9609,
          "y": 1040.6019,
          "zIndex": 324,
          "widthName": 74,
          "widthComment": 68,
          "color": ""
        },
        "meta": {
          "updateAt": 1769744606877,
          "createAt": 1769516073412
        }
      },
      "92QHjiK7WB1aIJMOCPIbC": {
        "id": "92QHjiK7WB1aIJMOCPIbC",
        "name": "items",
        "comment": "",
        "columnIds": [],
        "seqColumnIds": [],
        "ui": {
          "x": 411.373,
          "y": 959.3141,
          "zIndex": 354,
          "widthName": 60,
          "widthComment": 60,
          "color": ""
        },
        "meta": {
          "updateAt": 1769516468072,
          "createAt": 1769516460579
        }
      },
      "sl59DqkQiHdpea1EMLv-R": {
        "id": "sl59DqkQiHdpea1EMLv-R",
        "name": "badge",
        "comment": "배지",
        "columnIds": [
          "gObAQtNx1fP_irqgB37Ot",
          "2AqgPH_VVeYaPJ7tg7EvI",
          "hcRSzymqR2Z6hQ9HbwRQ6",
          "divpRdem6H7_EMAETWpe2"
        ],
        "seqColumnIds": [
          "gObAQtNx1fP_irqgB37Ot",
          "2AqgPH_VVeYaPJ7tg7EvI",
          "hcRSzymqR2Z6hQ9HbwRQ6",
          "divpRdem6H7_EMAETWpe2",
          "gDyQXFINDlNAEr80PoSbc"
        ],
        "ui": {
          "x": 11.25,
          "y": 1473.4594,
          "zIndex": 521,
          "widthName": 60,
          "widthComment": 60,
          "color": ""
        },
        "meta": {
          "updateAt": 1769571706753,
          "createAt": 1769571079475
        }
      },
      "pHxvDRevJXyNO9omgJdtS": {
        "id": "pHxvDRevJXyNO9omgJdtS",
        "name": "user_badge",
        "comment": "유저 배지",
        "columnIds": [
          "kf3XPeewE5ikb71DVg1zi",
          "z6UWEs14RZTnbySSuhtYL",
          "7V1toYkeSL1RMnKnK98ID",
          "VbKbxZ9omYaOjAilnwVHT",
          "hqTIp10iZnrDULrJjJfog"
        ],
        "seqColumnIds": [
          "kf3XPeewE5ikb71DVg1zi",
          "z6UWEs14RZTnbySSuhtYL",
          "xvTe_j0n4mqOC1_Sp_4B4",
          "7V1toYkeSL1RMnKnK98ID",
          "VbKbxZ9omYaOjAilnwVHT",
          "hqTIp10iZnrDULrJjJfog"
        ],
        "ui": {
          "x": -1.25,
          "y": 1160.8315,
          "zIndex": 600,
          "widthName": 69,
          "widthComment": 60,
          "color": ""
        },
        "meta": {
          "updateAt": 1769571702022,
          "createAt": 1769571339066
        }
      },
      "CKd0J5jyyS6BkdxLBP2mH": {
        "id": "CKd0J5jyyS6BkdxLBP2mH",
        "name": "items",
        "comment": "사용자 생성 아이템",
        "columnIds": [
          "Cg6PtHxSkBoKMiCshonY-",
          "kQjK_Z7n8C6qBnbFBpgHY",
          "119QbRTb0dex9xc7vY2iP",
          "1hoZkneiKyWmUEeuOdehp",
          "3j3z1ZdlaTGSaBGbK_4O3",
          "1I0zw4KaIw_goLJtCBO0W",
          "aIvji8ak_jjso8A6dZ57U",
          "hBgLoz5wMeWnNlQWWVuqX"
        ],
        "seqColumnIds": [
          "Cg6PtHxSkBoKMiCshonY-",
          "kQjK_Z7n8C6qBnbFBpgHY",
          "119QbRTb0dex9xc7vY2iP",
          "1hoZkneiKyWmUEeuOdehp",
          "3j3z1ZdlaTGSaBGbK_4O3",
          "1I0zw4KaIw_goLJtCBO0W",
          "aIvji8ak_jjso8A6dZ57U",
          "hBgLoz5wMeWnNlQWWVuqX",
          "aYUp0At97qlQ50oZMgUZS"
        ],
        "ui": {
          "x": 835.6494,
          "y": 1010.3384,
          "zIndex": 700,
          "widthName": 60,
          "widthComment": 92,
          "color": ""
        },
        "meta": {
          "updateAt": 1769744605310,
          "createAt": 1769612005428
        }
      },
      "ZZqHZvyPEOG31dM5HyoMZ": {
        "id": "ZZqHZvyPEOG31dM5HyoMZ",
        "name": "pack_wishlists",
        "comment": "팩 위시리스트",
        "columnIds": [
          "WN1aXCGsto8Tyt6C6olQ0",
          "dOK5IR4l7BOorgsXMyC3s",
          "szv4b63xO4XliXWOctoEy"
        ],
        "seqColumnIds": [
          "WN1aXCGsto8Tyt6C6olQ0",
          "IubxvL72QpTKHvJO3S2_R",
          "dOK5IR4l7BOorgsXMyC3s",
          "szv4b63xO4XliXWOctoEy"
        ],
        "ui": {
          "x": 533.3005,
          "y": 749.2237,
          "zIndex": 813,
          "widthName": 84,
          "widthComment": 68,
          "color": ""
        },
        "meta": {
          "updateAt": 1769744598778,
          "createAt": 1769613605290
        }
      },
      "PDSBscIUbI3lLRWMvjKsV": {
        "id": "PDSBscIUbI3lLRWMvjKsV",
        "name": "item_wishlists",
        "comment": "아이템 위시리스트",
        "columnIds": [
          "xs19zzcGT2XuhuXx23OnE",
          "LaJSQkeRHvz3EGve0cCKN",
          "4mGqpgDMSU2-eGJE3JXek"
        ],
        "seqColumnIds": [
          "xs19zzcGT2XuhuXx23OnE",
          "LaJSQkeRHvz3EGve0cCKN",
          "4mGqpgDMSU2-eGJE3JXek"
        ],
        "ui": {
          "x": 241.372,
          "y": 918.1721,
          "zIndex": 830,
          "widthName": 81,
          "widthComment": 88,
          "color": ""
        },
        "meta": {
          "updateAt": 1769744601259,
          "createAt": 1769613652883
        }
      }
    },
    "tableColumnEntities": {
      "12bIRpyyz6SYpal4thnLn": {
        "id": "12bIRpyyz6SYpal4thnLn",
        "tableId": "bJ7AOC6b5UBri3XKxWYJY",
        "name": "",
        "comment": "",
        "dataType": "",
        "default": "",
        "options": 0,
        "ui": {
          "keys": 0,
          "widthName": 60,
          "widthComment": 60,
          "widthDataType": 60,
          "widthDefault": 60
        },
        "meta": {
          "updateAt": 1769439122526,
          "createAt": 1769439122526
        }
      },
      "Y5sg76HQD1b4WUYJJ4V9G": {
        "id": "Y5sg76HQD1b4WUYJJ4V9G",
        "tableId": "bJ7AOC6b5UBri3XKxWYJY",
        "name": "id",
        "comment": "PK",
        "dataType": "BIGINT",
        "default": "",
        "options": 10,
        "ui": {
          "keys": 1,
          "widthName": 60,
          "widthComment": 60,
          "widthDataType": 60,
          "widthDefault": 60
        },
        "meta": {
          "updateAt": 1769439167105,
          "createAt": 1769439131853
        }
      },
      "ZYNf3lizgpnCOehkqkNnV": {
        "id": "ZYNf3lizgpnCOehkqkNnV",
        "tableId": "bJ7AOC6b5UBri3XKxWYJY",
        "name": "nickname",
        "comment": "사용자 닉네임",
        "dataType": "VARCHAR(10)",
        "default": "",
        "options": 8,
        "ui": {
          "keys": 0,
          "widthName": 60,
          "widthComment": 68,
          "widthDataType": 81,
          "widthDefault": 60
        },
        "meta": {
          "updateAt": 1769509116015,
          "createAt": 1769508413958
        }
      },
      "JLymQu7fjq50FAAQE8qf9": {
        "id": "JLymQu7fjq50FAAQE8qf9",
        "tableId": "bJ7AOC6b5UBri3XKxWYJY",
        "name": "gender",
        "comment": "사용자 성별",
        "dataType": "ENUM",
        "default": "",
        "options": 0,
        "ui": {
          "keys": 0,
          "widthName": 60,
          "widthComment": 60,
          "widthDataType": 60,
          "widthDefault": 60
        },
        "meta": {
          "updateAt": 1769611103373,
          "createAt": 1769509119165
        }
      },
      "9gFNL8CfIs6lwKrGWB4E3": {
        "id": "9gFNL8CfIs6lwKrGWB4E3",
        "tableId": "bJ7AOC6b5UBri3XKxWYJY",
        "name": "auth_provider",
        "comment": "사용자 소셜로그인 인증 제공수단",
        "dataType": "ENUM",
        "default": "",
        "options": 0,
        "ui": {
          "keys": 0,
          "widthName": 81,
          "widthComment": 157,
          "widthDataType": 60,
          "widthDefault": 60
        },
        "meta": {
          "updateAt": 1769611105823,
          "createAt": 1769509259893
        }
      },
      "38Djba51KwYs2dMmjf8Ap": {
        "id": "38Djba51KwYs2dMmjf8Ap",
        "tableId": "bJ7AOC6b5UBri3XKxWYJY",
        "name": "occupation",
        "comment": "사용자 직군",
        "dataType": "ENUM",
        "default": "",
        "options": 0,
        "ui": {
          "keys": 0,
          "widthName": 65,
          "widthComment": 60,
          "widthDataType": 60,
          "widthDefault": 60
        },
        "meta": {
          "updateAt": 1769611107397,
          "createAt": 1769509439021
        }
      },
      "23yFW8CX4fDCJD-2RV-8-": {
        "id": "23yFW8CX4fDCJD-2RV-8-",
        "tableId": "3APtNOasTm-e0OA6a9FNY",
        "name": "",
        "comment": "",
        "dataType": "",
        "default": "",
        "options": 0,
        "ui": {
          "keys": 0,
          "widthName": 60,
          "widthComment": 60,
          "widthDataType": 60,
          "widthDefault": 60
        },
        "meta": {
          "updateAt": 1769512952247,
          "createAt": 1769512952247
        }
      },
      "Yik8C7n_4LANoofIXLQeJ": {
        "id": "Yik8C7n_4LANoofIXLQeJ",
        "tableId": "3APtNOasTm-e0OA6a9FNY",
        "name": "id",
        "comment": "PK",
        "dataType": "BIGINT",
        "default": "",
        "options": 10,
        "ui": {
          "keys": 1,
          "widthName": 60,
          "widthComment": 60,
          "widthDataType": 60,
          "widthDefault": 60
        },
        "meta": {
          "updateAt": 1769513001910,
          "createAt": 1769512991957
        }
      },
      "2xZju6Dp2JIgXIVCgxpLK": {
        "id": "2xZju6Dp2JIgXIVCgxpLK",
        "tableId": "3APtNOasTm-e0OA6a9FNY",
        "name": "interest_categories",
        "comment": "",
        "dataType": "",
        "default": "",
        "options": 0,
        "ui": {
          "keys": 0,
          "widthName": 111,
          "widthComment": 60,
          "widthDataType": 60,
          "widthDefault": 60
        },
        "meta": {
          "updateAt": 1769513007612,
          "createAt": 1769513007611
        }
      },
      "L8q3tzdncz7rxAHTHYpq5": {
        "id": "L8q3tzdncz7rxAHTHYpq5",
        "tableId": "3APtNOasTm-e0OA6a9FNY",
        "name": "",
        "comment": "",
        "dataType": "",
        "default": "",
        "options": 0,
        "ui": {
          "keys": 0,
          "widthName": 60,
          "widthComment": 60,
          "widthDataType": 60,
          "widthDefault": 60
        },
        "meta": {
          "updateAt": 1769513007612,
          "createAt": 1769513007612
        }
      },
      "EsISW6Mr9DXlP36DBwsJF": {
        "id": "EsISW6Mr9DXlP36DBwsJF",
        "tableId": "3APtNOasTm-e0OA6a9FNY",
        "name": "interest_categories",
        "comment": "",
        "dataType": "",
        "default": "",
        "options": 0,
        "ui": {
          "keys": 0,
          "widthName": 111,
          "widthComment": 60,
          "widthDataType": 60,
          "widthDefault": 60
        },
        "meta": {
          "updateAt": 1769513010786,
          "createAt": 1769513010785
        }
      },
      "RloSc9qIoi_5JuwqEyJJb": {
        "id": "RloSc9qIoi_5JuwqEyJJb",
        "tableId": "3APtNOasTm-e0OA6a9FNY",
        "name": "",
        "comment": "",
        "dataType": "",
        "default": "",
        "options": 0,
        "ui": {
          "keys": 0,
          "widthName": 60,
          "widthComment": 60,
          "widthDataType": 60,
          "widthDefault": 60
        },
        "meta": {
          "updateAt": 1769513010786,
          "createAt": 1769513010786
        }
      },
      "_kFZ7ZkPhzn-uJ98MLKU_": {
        "id": "_kFZ7ZkPhzn-uJ98MLKU_",
        "tableId": "3APtNOasTm-e0OA6a9FNY",
        "name": "interest_categories",
        "comment": "",
        "dataType": "",
        "default": "",
        "options": 0,
        "ui": {
          "keys": 0,
          "widthName": 111,
          "widthComment": 60,
          "widthDataType": 60,
          "widthDefault": 60
        },
        "meta": {
          "updateAt": 1769513011873,
          "createAt": 1769513011873
        }
      },
      "iAvvIQF3trv6BKYOTp2SI": {
        "id": "iAvvIQF3trv6BKYOTp2SI",
        "tableId": "3APtNOasTm-e0OA6a9FNY",
        "name": "",
        "comment": "",
        "dataType": "",
        "default": "",
        "options": 0,
        "ui": {
          "keys": 0,
          "widthName": 60,
          "widthComment": 60,
          "widthDataType": 60,
          "widthDefault": 60
        },
        "meta": {
          "updateAt": 1769513011873,
          "createAt": 1769513011873
        }
      },
      "ZGvFOIXwQ1aP1SQKQ4I5i": {
        "id": "ZGvFOIXwQ1aP1SQKQ4I5i",
        "tableId": "DsMm1UbPEc01xHb0e5kDp",
        "name": "id",
        "comment": "PK",
        "dataType": "BIGINT",
        "default": "",
        "options": 10,
        "ui": {
          "keys": 1,
          "widthName": 60,
          "widthComment": 60,
          "widthDataType": 60,
          "widthDefault": 60
        },
        "meta": {
          "updateAt": 1769513066918,
          "createAt": 1769513056056
        }
      },
      "ZcBlR_Wxtb0eX2onfhMVR": {
        "id": "ZcBlR_Wxtb0eX2onfhMVR",
        "tableId": "_B8cZ5qmp5gvIdren79eJ",
        "name": "id",
        "comment": "PK",
        "dataType": "BIGINT",
        "default": "",
        "options": 10,
        "ui": {
          "keys": 1,
          "widthName": 60,
          "widthComment": 60,
          "widthDataType": 60,
          "widthDefault": 60
        },
        "meta": {
          "updateAt": 1769513227349,
          "createAt": 1769513218721
        }
      },
      "-6nKsN3M0PV49ZxBTkPGI": {
        "id": "-6nKsN3M0PV49ZxBTkPGI",
        "tableId": "t-nhS9VuC9Mb4hcV-9Yt2",
        "name": "id",
        "comment": "PK",
        "dataType": "BIGINT",
        "default": "",
        "options": 10,
        "ui": {
          "keys": 1,
          "widthName": 60,
          "widthComment": 60,
          "widthDataType": 60,
          "widthDefault": 60
        },
        "meta": {
          "updateAt": 1769513263880,
          "createAt": 1769513246737
        }
      },
      "4h8DnXWfcsrFOMYoCcyGC": {
        "id": "4h8DnXWfcsrFOMYoCcyGC",
        "tableId": "t-nhS9VuC9Mb4hcV-9Yt2",
        "name": "",
        "comment": "",
        "dataType": "",
        "default": "",
        "options": 0,
        "ui": {
          "keys": 0,
          "widthName": 60,
          "widthComment": 60,
          "widthDataType": 60,
          "widthDefault": 60
        },
        "meta": {
          "updateAt": 1769513260792,
          "createAt": 1769513260792
        }
      },
      "zc6g-Z520uRGElgQm_DuH": {
        "id": "zc6g-Z520uRGElgQm_DuH",
        "tableId": "t-nhS9VuC9Mb4hcV-9Yt2",
        "name": "user_id",
        "comment": "FK",
        "dataType": "BIGINT",
        "default": "",
        "options": 8,
        "ui": {
          "keys": 2,
          "widthName": 60,
          "widthComment": 60,
          "widthDataType": 60,
          "widthDefault": 60
        },
        "meta": {
          "updateAt": 1769513464148,
          "createAt": 1769513371899
        }
      },
      "uitMLZ80N_hGuoxqW-LEX": {
        "id": "uitMLZ80N_hGuoxqW-LEX",
        "tableId": "t-nhS9VuC9Mb4hcV-9Yt2",
        "name": "situation_category_id",
        "comment": "FK",
        "dataType": "BIGINT",
        "default": "",
        "options": 8,
        "ui": {
          "keys": 2,
          "widthName": 124,
          "widthComment": 60,
          "widthDataType": 60,
          "widthDefault": 60
        },
        "meta": {
          "updateAt": 1769513468262,
          "createAt": 1769513401131
        }
      },
      "jgbj5Ow5Oi__-xi8rXagR": {
        "id": "jgbj5Ow5Oi__-xi8rXagR",
        "tableId": "_B8cZ5qmp5gvIdren79eJ",
        "name": "user_id",
        "comment": "FK",
        "dataType": "BIGINT",
        "default": "",
        "options": 8,
        "ui": {
          "keys": 2,
          "widthName": 60,
          "widthComment": 60,
          "widthDataType": 60,
          "widthDefault": 60
        },
        "meta": {
          "updateAt": 1769513522574,
          "createAt": 1769513517527
        }
      },
      "dBb5AGYLM8jVGJeQwkprV": {
        "id": "dBb5AGYLM8jVGJeQwkprV",
        "tableId": "_B8cZ5qmp5gvIdren79eJ",
        "name": "interest_category_id",
        "comment": "PK",
        "dataType": "BIGINT",
        "default": "",
        "options": 8,
        "ui": {
          "keys": 2,
          "widthName": 118,
          "widthComment": 60,
          "widthDataType": 60,
          "widthDefault": 60
        },
        "meta": {
          "updateAt": 1769513539657,
          "createAt": 1769513533078
        }
      },
      "SecDLSP7hc7TMIxoGvMON": {
        "id": "SecDLSP7hc7TMIxoGvMON",
        "tableId": "cBh8ORWDjyegNE57Iuv2o",
        "name": "id",
        "comment": "PK",
        "dataType": "BIGINT",
        "default": "",
        "options": 10,
        "ui": {
          "keys": 1,
          "widthName": 60,
          "widthComment": 60,
          "widthDataType": 60,
          "widthDefault": 60
        },
        "meta": {
          "updateAt": 1769514026049,
          "createAt": 1769514012226
        }
      },
      "q4XsS4TgYBxoL-nuye3fo": {
        "id": "q4XsS4TgYBxoL-nuye3fo",
        "tableId": "cBh8ORWDjyegNE57Iuv2o",
        "name": "",
        "comment": "",
        "dataType": "",
        "default": "",
        "options": 0,
        "ui": {
          "keys": 0,
          "widthName": 60,
          "widthComment": 60,
          "widthDataType": 60,
          "widthDefault": 60
        },
        "meta": {
          "updateAt": 1769514040160,
          "createAt": 1769514040160
        }
      },
      "nqZpfXMdmHOsL6RbUUM2f": {
        "id": "nqZpfXMdmHOsL6RbUUM2f",
        "tableId": "qGNzk1VxwkfSKRvH8KQ8O",
        "name": "id",
        "comment": "PK",
        "dataType": "BIGINT",
        "default": "",
        "options": 10,
        "ui": {
          "keys": 1,
          "widthName": 60,
          "widthComment": 60,
          "widthDataType": 60,
          "widthDefault": 60
        },
        "meta": {
          "updateAt": 1769514605391,
          "createAt": 1769514597346
        }
      },
      "6fqObkZvz22PfHUOndUjb": {
        "id": "6fqObkZvz22PfHUOndUjb",
        "tableId": "qGNzk1VxwkfSKRvH8KQ8O",
        "name": "interest_category_id",
        "comment": "FK",
        "dataType": "BIGINT",
        "default": "",
        "options": 8,
        "ui": {
          "keys": 0,
          "widthName": 118,
          "widthComment": 60,
          "widthDataType": 60,
          "widthDefault": 60
        },
        "meta": {
          "updateAt": 1769514698664,
          "createAt": 1769514618641
        }
      },
      "Ictq5yX_96r7zLmYbT9MC": {
        "id": "Ictq5yX_96r7zLmYbT9MC",
        "tableId": "YqpgNdCUwXpWWFYMZkHj0",
        "name": "id",
        "comment": "PK",
        "dataType": "BIGINT",
        "default": "",
        "options": 10,
        "ui": {
          "keys": 1,
          "widthName": 60,
          "widthComment": 60,
          "widthDataType": 60,
          "widthDefault": 60
        },
        "meta": {
          "updateAt": 1769514705561,
          "createAt": 1769514687408
        }
      },
      "CPB3G6oYATPVAK4cDCk-Z": {
        "id": "CPB3G6oYATPVAK4cDCk-Z",
        "tableId": "YqpgNdCUwXpWWFYMZkHj0",
        "name": "",
        "comment": "",
        "dataType": "",
        "default": "",
        "options": 10,
        "ui": {
          "keys": 1,
          "widthName": 60,
          "widthComment": 60,
          "widthDataType": 60,
          "widthDefault": 60
        },
        "meta": {
          "updateAt": 1769514702931,
          "createAt": 1769514700840
        }
      },
      "bP5dLdS8N3D_0oczoMX8e": {
        "id": "bP5dLdS8N3D_0oczoMX8e",
        "tableId": "YqpgNdCUwXpWWFYMZkHj0",
        "name": "situation_category_id",
        "comment": "FK",
        "dataType": "BIGINT",
        "default": "",
        "options": 8,
        "ui": {
          "keys": 0,
          "widthName": 124,
          "widthComment": 60,
          "widthDataType": 60,
          "widthDefault": 60
        },
        "meta": {
          "updateAt": 1769514725927,
          "createAt": 1769514713298
        }
      },
      "Lf-H19PaEikcDbGd-xXV4": {
        "id": "Lf-H19PaEikcDbGd-xXV4",
        "tableId": "cBh8ORWDjyegNE57Iuv2o",
        "name": "user_id",
        "comment": "FK",
        "dataType": "BIGINT",
        "default": "",
        "options": 8,
        "ui": {
          "keys": 2,
          "widthName": 60,
          "widthComment": 60,
          "widthDataType": 60,
          "widthDefault": 60
        },
        "meta": {
          "updateAt": 1769514852126,
          "createAt": 1769514843010
        }
      },
      "KxA9qeagDOFxgyEA_Ma6i": {
        "id": "KxA9qeagDOFxgyEA_Ma6i",
        "tableId": "cBh8ORWDjyegNE57Iuv2o",
        "name": "situation_detail_id",
        "comment": "FK",
        "dataType": "BIGINT",
        "default": "",
        "options": 8,
        "ui": {
          "keys": 0,
          "widthName": 106,
          "widthComment": 60,
          "widthDataType": 60,
          "widthDefault": 60
        },
        "meta": {
          "updateAt": 1769515021663,
          "createAt": 1769514920021
        }
      },
      "TEr5ElEuN_yR4rXy7aTg4": {
        "id": "TEr5ElEuN_yR4rXy7aTg4",
        "tableId": "cBh8ORWDjyegNE57Iuv2o",
        "name": "interest_detail_id",
        "comment": "FK",
        "dataType": "BIGINT",
        "default": "",
        "options": 8,
        "ui": {
          "keys": 0,
          "widthName": 100,
          "widthComment": 60,
          "widthDataType": 60,
          "widthDefault": 60
        },
        "meta": {
          "updateAt": 1769515041150,
          "createAt": 1769514977445
        }
      },
      "o_msB0MbTGb2uhC3SrOJP": {
        "id": "o_msB0MbTGb2uhC3SrOJP",
        "tableId": "cBh8ORWDjyegNE57Iuv2o",
        "name": "title",
        "comment": "팩 타이틀",
        "dataType": "VARCHAR(10)",
        "default": "",
        "options": 0,
        "ui": {
          "keys": 0,
          "widthName": 60,
          "widthComment": 60,
          "widthDataType": 81,
          "widthDefault": 60
        },
        "meta": {
          "updateAt": 1769612431459,
          "createAt": 1769515058187
        }
      },
      "WhhmSvzblAHFpDIpavKae": {
        "id": "WhhmSvzblAHFpDIpavKae",
        "tableId": "9Ran1wBWSEnygQOVVznXd",
        "name": "",
        "comment": "",
        "dataType": "",
        "default": "",
        "options": 0,
        "ui": {
          "keys": 0,
          "widthName": 60,
          "widthComment": 60,
          "widthDataType": 60,
          "widthDefault": 60
        },
        "meta": {
          "updateAt": 1769516369981,
          "createAt": 1769516369981
        }
      },
      "7FK0ufqsPBeAHm8jVTLKL": {
        "id": "7FK0ufqsPBeAHm8jVTLKL",
        "tableId": "9Ran1wBWSEnygQOVVznXd",
        "name": "id",
        "comment": "PK",
        "dataType": "BIGINT",
        "default": "",
        "options": 10,
        "ui": {
          "keys": 1,
          "widthName": 60,
          "widthComment": 60,
          "widthDataType": 60,
          "widthDefault": 60
        },
        "meta": {
          "updateAt": 1769516384665,
          "createAt": 1769516377819
        }
      },
      "i8Y6uANHTxdv3eWHTg1rP": {
        "id": "i8Y6uANHTxdv3eWHTg1rP",
        "tableId": "9Ran1wBWSEnygQOVVznXd",
        "name": "image_path",
        "comment": "아이템 이미지 경로",
        "dataType": "TEXT",
        "default": "",
        "options": 0,
        "ui": {
          "keys": 0,
          "widthName": 68,
          "widthComment": 92,
          "widthDataType": 60,
          "widthDefault": 60
        },
        "meta": {
          "updateAt": 1769613387993,
          "createAt": 1769516387548
        }
      },
      "2w5ryMWNqG2Eqg6gJwZN9": {
        "id": "2w5ryMWNqG2Eqg6gJwZN9",
        "tableId": "9Ran1wBWSEnygQOVVznXd",
        "name": "pack_id",
        "comment": "FK",
        "dataType": "BIGINT",
        "default": "",
        "options": 8,
        "ui": {
          "keys": 0,
          "widthName": 60,
          "widthComment": 60,
          "widthDataType": 60,
          "widthDefault": 60
        },
        "meta": {
          "updateAt": 1769516444232,
          "createAt": 1769516437876
        }
      },
      "tXY5I8Nxdkkx4I9-pIjyE": {
        "id": "tXY5I8Nxdkkx4I9-pIjyE",
        "tableId": "bJ7AOC6b5UBri3XKxWYJY",
        "name": "age_group",
        "comment": "연령대",
        "dataType": "ENUM",
        "default": "",
        "options": 0,
        "ui": {
          "keys": 0,
          "widthName": 62,
          "widthComment": 60,
          "widthDataType": 60,
          "widthDefault": 60
        },
        "meta": {
          "updateAt": 1769611108719,
          "createAt": 1769569645420
        }
      },
      "_3UvUG5U39AngHYBHTyhJ": {
        "id": "_3UvUG5U39AngHYBHTyhJ",
        "tableId": "3APtNOasTm-e0OA6a9FNY",
        "name": "name",
        "comment": "카테고리 이름",
        "dataType": "VARCHAR(50)",
        "default": "",
        "options": 8,
        "ui": {
          "keys": 0,
          "widthName": 60,
          "widthComment": 68,
          "widthDataType": 83,
          "widthDefault": 60
        },
        "meta": {
          "updateAt": 1769744489500,
          "createAt": 1769569845715
        }
      },
      "zDM1dgenIeHjC7RxZnb8J": {
        "id": "zDM1dgenIeHjC7RxZnb8J",
        "tableId": "DsMm1UbPEc01xHb0e5kDp",
        "name": "name",
        "comment": "카테고리 이름",
        "dataType": "VARCHAR(50)",
        "default": "",
        "options": 8,
        "ui": {
          "keys": 0,
          "widthName": 60,
          "widthComment": 68,
          "widthDataType": 83,
          "widthDefault": 60
        },
        "meta": {
          "updateAt": 1769744452996,
          "createAt": 1769569873929
        }
      },
      "rREWLc4BJCj_zo6K1zQz4": {
        "id": "rREWLc4BJCj_zo6K1zQz4",
        "tableId": "YqpgNdCUwXpWWFYMZkHj0",
        "name": "name",
        "comment": "이름",
        "dataType": "VARCHAR(255)",
        "default": "",
        "options": 8,
        "ui": {
          "keys": 0,
          "widthName": 60,
          "widthComment": 60,
          "widthDataType": 90,
          "widthDefault": 60
        },
        "meta": {
          "updateAt": 1769570604701,
          "createAt": 1769570562673
        }
      },
      "x4ZDUtpwRvpMn5Jqa3TJY": {
        "id": "x4ZDUtpwRvpMn5Jqa3TJY",
        "tableId": "qGNzk1VxwkfSKRvH8KQ8O",
        "name": "name",
        "comment": "이름",
        "dataType": "VARCHAR(255)",
        "default": "",
        "options": 8,
        "ui": {
          "keys": 0,
          "widthName": 60,
          "widthComment": 60,
          "widthDataType": 90,
          "widthDefault": 60
        },
        "meta": {
          "updateAt": 1769570627706,
          "createAt": 1769570611746
        }
      },
      "aJZyAWdElcgJ1lktVMOgu": {
        "id": "aJZyAWdElcgJ1lktVMOgu",
        "tableId": "bJ7AOC6b5UBri3XKxWYJY",
        "name": "profile_image",
        "comment": "프로필 이미지",
        "dataType": "TEXT",
        "default": "",
        "options": 0,
        "ui": {
          "keys": 0,
          "widthName": 79,
          "widthComment": 68,
          "widthDataType": 60,
          "widthDefault": 60
        },
        "meta": {
          "updateAt": 1769611109999,
          "createAt": 1769570682075
        }
      },
      "gObAQtNx1fP_irqgB37Ot": {
        "id": "gObAQtNx1fP_irqgB37Ot",
        "tableId": "sl59DqkQiHdpea1EMLv-R",
        "name": "id",
        "comment": "PK",
        "dataType": "BIGINT",
        "default": "",
        "options": 10,
        "ui": {
          "keys": 1,
          "widthName": 60,
          "widthComment": 60,
          "widthDataType": 60,
          "widthDefault": 60
        },
        "meta": {
          "updateAt": 1769571116955,
          "createAt": 1769571099229
        }
      },
      "2AqgPH_VVeYaPJ7tg7EvI": {
        "id": "2AqgPH_VVeYaPJ7tg7EvI",
        "tableId": "sl59DqkQiHdpea1EMLv-R",
        "name": "name",
        "comment": "배지 이름",
        "dataType": "VARCHAR",
        "default": "",
        "options": 8,
        "ui": {
          "keys": 0,
          "widthName": 60,
          "widthComment": 60,
          "widthDataType": 60,
          "widthDefault": 60
        },
        "meta": {
          "updateAt": 1769571484809,
          "createAt": 1769571118071
        }
      },
      "hcRSzymqR2Z6hQ9HbwRQ6": {
        "id": "hcRSzymqR2Z6hQ9HbwRQ6",
        "tableId": "sl59DqkQiHdpea1EMLv-R",
        "name": "description",
        "comment": "설명",
        "dataType": "TEXT",
        "default": "",
        "options": 8,
        "ui": {
          "keys": 0,
          "widthName": 65,
          "widthComment": 60,
          "widthDataType": 60,
          "widthDefault": 60
        },
        "meta": {
          "updateAt": 1769571301649,
          "createAt": 1769571176622
        }
      },
      "divpRdem6H7_EMAETWpe2": {
        "id": "divpRdem6H7_EMAETWpe2",
        "tableId": "sl59DqkQiHdpea1EMLv-R",
        "name": "icon_image",
        "comment": "배지 이미지",
        "dataType": "TEXT",
        "default": "",
        "options": 8,
        "ui": {
          "keys": 0,
          "widthName": 67,
          "widthComment": 60,
          "widthDataType": 60,
          "widthDefault": 60
        },
        "meta": {
          "updateAt": 1769571317826,
          "createAt": 1769571303480
        }
      },
      "kf3XPeewE5ikb71DVg1zi": {
        "id": "kf3XPeewE5ikb71DVg1zi",
        "tableId": "pHxvDRevJXyNO9omgJdtS",
        "name": "id",
        "comment": "PK",
        "dataType": "BIGINT",
        "default": "",
        "options": 10,
        "ui": {
          "keys": 1,
          "widthName": 60,
          "widthComment": 60,
          "widthDataType": 60,
          "widthDefault": 60
        },
        "meta": {
          "updateAt": 1769571370251,
          "createAt": 1769571357710
        }
      },
      "xvTe_j0n4mqOC1_Sp_4B4": {
        "id": "xvTe_j0n4mqOC1_Sp_4B4",
        "tableId": "pHxvDRevJXyNO9omgJdtS",
        "name": "user_id",
        "comment": "FK",
        "dataType": "BIGINT",
        "default": "",
        "options": 8,
        "ui": {
          "keys": 0,
          "widthName": 60,
          "widthComment": 60,
          "widthDataType": 60,
          "widthDefault": 60
        },
        "meta": {
          "updateAt": 1769571385036,
          "createAt": 1769571373901
        }
      },
      "z6UWEs14RZTnbySSuhtYL": {
        "id": "z6UWEs14RZTnbySSuhtYL",
        "tableId": "pHxvDRevJXyNO9omgJdtS",
        "name": "acquired_at",
        "comment": "배지 획득 시각",
        "dataType": "TIMESTAMP",
        "default": "",
        "options": 8,
        "ui": {
          "keys": 0,
          "widthName": 69,
          "widthComment": 71,
          "widthDataType": 71,
          "widthDefault": 60
        },
        "meta": {
          "updateAt": 1769571424111,
          "createAt": 1769571395703
        }
      },
      "7V1toYkeSL1RMnKnK98ID": {
        "id": "7V1toYkeSL1RMnKnK98ID",
        "tableId": "pHxvDRevJXyNO9omgJdtS",
        "name": "is_represent",
        "comment": "대표 배지 여부",
        "dataType": "BOOLEAN",
        "default": "",
        "options": 8,
        "ui": {
          "keys": 0,
          "widthName": 72,
          "widthComment": 71,
          "widthDataType": 60,
          "widthDefault": 60
        },
        "meta": {
          "updateAt": 1769571456674,
          "createAt": 1769571441762
        }
      },
      "gDyQXFINDlNAEr80PoSbc": {
        "id": "gDyQXFINDlNAEr80PoSbc",
        "tableId": "sl59DqkQiHdpea1EMLv-R",
        "name": "id",
        "comment": "PK",
        "dataType": "BIGINT",
        "default": "",
        "options": 8,
        "ui": {
          "keys": 0,
          "widthName": 60,
          "widthComment": 60,
          "widthDataType": 60,
          "widthDefault": 60
        },
        "meta": {
          "updateAt": 1769571619489,
          "createAt": 1769571619488
        }
      },
      "VbKbxZ9omYaOjAilnwVHT": {
        "id": "VbKbxZ9omYaOjAilnwVHT",
        "tableId": "pHxvDRevJXyNO9omgJdtS",
        "name": "badge_id",
        "comment": "PK",
        "dataType": "BIGINT",
        "default": "",
        "options": 8,
        "ui": {
          "keys": 2,
          "widthName": 60,
          "widthComment": 60,
          "widthDataType": 60,
          "widthDefault": 60
        },
        "meta": {
          "updateAt": 1769571677503,
          "createAt": 1769571664015
        }
      },
      "hqTIp10iZnrDULrJjJfog": {
        "id": "hqTIp10iZnrDULrJjJfog",
        "tableId": "pHxvDRevJXyNO9omgJdtS",
        "name": "id",
        "comment": "PK",
        "dataType": "BIGINT",
        "default": "",
        "options": 8,
        "ui": {
          "keys": 2,
          "widthName": 60,
          "widthComment": 60,
          "widthDataType": 60,
          "widthDefault": 60
        },
        "meta": {
          "updateAt": 1769571692649,
          "createAt": 1769571692649
        }
      },
      "qelqDKuxvmS8XcL1dHBDd": {
        "id": "qelqDKuxvmS8XcL1dHBDd",
        "tableId": "bJ7AOC6b5UBri3XKxWYJY",
        "name": "email",
        "comment": "사용자 이메일",
        "dataType": "VARCHAR(50)",
        "default": "",
        "options": 8,
        "ui": {
          "keys": 0,
          "widthName": 60,
          "widthComment": 68,
          "widthDataType": 83,
          "widthDefault": 60
        },
        "meta": {
          "updateAt": 1769593956222,
          "createAt": 1769593892055
        }
      },
      "Cg6PtHxSkBoKMiCshonY-": {
        "id": "Cg6PtHxSkBoKMiCshonY-",
        "tableId": "CKd0J5jyyS6BkdxLBP2mH",
        "name": "id",
        "comment": "PK",
        "dataType": "BIGINT",
        "default": "",
        "options": 10,
        "ui": {
          "keys": 1,
          "widthName": 60,
          "widthComment": 60,
          "widthDataType": 60,
          "widthDefault": 60
        },
        "meta": {
          "updateAt": 1769612416504,
          "createAt": 1769612016801
        }
      },
      "119QbRTb0dex9xc7vY2iP": {
        "id": "119QbRTb0dex9xc7vY2iP",
        "tableId": "CKd0J5jyyS6BkdxLBP2mH",
        "name": "title",
        "comment": "아이템 타이틀",
        "dataType": "VARCHAR(25)",
        "default": "",
        "options": 8,
        "ui": {
          "keys": 0,
          "widthName": 60,
          "widthComment": 68,
          "widthDataType": 82,
          "widthDefault": 60
        },
        "meta": {
          "updateAt": 1769612435360,
          "createAt": 1769612028247
        }
      },
      "1hoZkneiKyWmUEeuOdehp": {
        "id": "1hoZkneiKyWmUEeuOdehp",
        "tableId": "CKd0J5jyyS6BkdxLBP2mH",
        "name": "brand",
        "comment": "아이템 브랜드",
        "dataType": "VARCHAR(25)",
        "default": "",
        "options": 0,
        "ui": {
          "keys": 0,
          "widthName": 60,
          "widthComment": 68,
          "widthDataType": 82,
          "widthDefault": 60
        },
        "meta": {
          "updateAt": 1769612450600,
          "createAt": 1769612435635
        }
      },
      "3j3z1ZdlaTGSaBGbK_4O3": {
        "id": "3j3z1ZdlaTGSaBGbK_4O3",
        "tableId": "CKd0J5jyyS6BkdxLBP2mH",
        "name": "review",
        "comment": "아이템 리뷰",
        "dataType": "VARCHAR(100)",
        "default": "",
        "options": 0,
        "ui": {
          "keys": 0,
          "widthName": 60,
          "widthComment": 60,
          "widthDataType": 89,
          "widthDefault": 60
        },
        "meta": {
          "updateAt": 1769613220005,
          "createAt": 1769612453812
        }
      },
      "1I0zw4KaIw_goLJtCBO0W": {
        "id": "1I0zw4KaIw_goLJtCBO0W",
        "tableId": "CKd0J5jyyS6BkdxLBP2mH",
        "name": "satisfaction",
        "comment": "아이템 만족도",
        "dataType": "ENUM",
        "default": "",
        "options": 8,
        "ui": {
          "keys": 0,
          "widthName": 68,
          "widthComment": 68,
          "widthDataType": 60,
          "widthDefault": 60
        },
        "meta": {
          "updateAt": 1769613243253,
          "createAt": 1769613220347
        }
      },
      "aIvji8ak_jjso8A6dZ57U": {
        "id": "aIvji8ak_jjso8A6dZ57U",
        "tableId": "CKd0J5jyyS6BkdxLBP2mH",
        "name": "use_period",
        "comment": "아이템 사용기간",
        "dataType": "ENUM",
        "default": "",
        "options": 8,
        "ui": {
          "keys": 0,
          "widthName": 65,
          "widthComment": 78,
          "widthDataType": 60,
          "widthDefault": 60
        },
        "meta": {
          "updateAt": 1769613262534,
          "createAt": 1769613243484
        }
      },
      "hBgLoz5wMeWnNlQWWVuqX": {
        "id": "hBgLoz5wMeWnNlQWWVuqX",
        "tableId": "CKd0J5jyyS6BkdxLBP2mH",
        "name": "purchase",
        "comment": "아이템 구매처",
        "dataType": "VARCHAR(25)",
        "default": "",
        "options": 0,
        "ui": {
          "keys": 0,
          "widthName": 60,
          "widthComment": 68,
          "widthDataType": 82,
          "widthDefault": 60
        },
        "meta": {
          "updateAt": 1769613315833,
          "createAt": 1769613262930
        }
      },
      "kQjK_Z7n8C6qBnbFBpgHY": {
        "id": "kQjK_Z7n8C6qBnbFBpgHY",
        "tableId": "CKd0J5jyyS6BkdxLBP2mH",
        "name": "pack_id",
        "comment": "FK",
        "dataType": "BIGINT",
        "default": "",
        "options": 8,
        "ui": {
          "keys": 2,
          "widthName": 60,
          "widthComment": 60,
          "widthDataType": 60,
          "widthDefault": 60
        },
        "meta": {
          "updateAt": 1769613340727,
          "createAt": 1769613327996
        }
      },
      "3bjIvqWdn__100c0zx3xo": {
        "id": "3bjIvqWdn__100c0zx3xo",
        "tableId": "9Ran1wBWSEnygQOVVznXd",
        "name": "item_id",
        "comment": "FK",
        "dataType": "BIGINT",
        "default": "",
        "options": 8,
        "ui": {
          "keys": 2,
          "widthName": 60,
          "widthComment": 60,
          "widthDataType": 60,
          "widthDefault": 60
        },
        "meta": {
          "updateAt": 1769613382159,
          "createAt": 1769613371851
        }
      },
      "Y_atxh8Yf_vJGL9u0Vysg": {
        "id": "Y_atxh8Yf_vJGL9u0Vysg",
        "tableId": "cBh8ORWDjyegNE57Iuv2o",
        "name": "like",
        "comment": "팩 좋아요",
        "dataType": "INT",
        "default": "0",
        "options": 8,
        "ui": {
          "keys": 0,
          "widthName": 60,
          "widthComment": 60,
          "widthDataType": 60,
          "widthDefault": 60
        },
        "meta": {
          "updateAt": 1769613533145,
          "createAt": 1769613498883
        }
      },
      "aYUp0At97qlQ50oZMgUZS": {
        "id": "aYUp0At97qlQ50oZMgUZS",
        "tableId": "CKd0J5jyyS6BkdxLBP2mH",
        "name": "like",
        "comment": "아이템 좋아요",
        "dataType": "INT",
        "default": "0",
        "options": 8,
        "ui": {
          "keys": 0,
          "widthName": 60,
          "widthComment": 68,
          "widthDataType": 60,
          "widthDefault": 60
        },
        "meta": {
          "updateAt": 1769613555136,
          "createAt": 1769613539817
        }
      },
      "WN1aXCGsto8Tyt6C6olQ0": {
        "id": "WN1aXCGsto8Tyt6C6olQ0",
        "tableId": "ZZqHZvyPEOG31dM5HyoMZ",
        "name": "id",
        "comment": "PK",
        "dataType": "BIGINT",
        "default": "",
        "options": 10,
        "ui": {
          "keys": 1,
          "widthName": 60,
          "widthComment": 60,
          "widthDataType": 60,
          "widthDefault": 60
        },
        "meta": {
          "updateAt": 1769613644693,
          "createAt": 1769613634366
        }
      },
      "xs19zzcGT2XuhuXx23OnE": {
        "id": "xs19zzcGT2XuhuXx23OnE",
        "tableId": "PDSBscIUbI3lLRWMvjKsV",
        "name": "id",
        "comment": "PK",
        "dataType": "BIGINT",
        "default": "",
        "options": 10,
        "ui": {
          "keys": 1,
          "widthName": 60,
          "widthComment": 60,
          "widthDataType": 60,
          "widthDefault": 60
        },
        "meta": {
          "updateAt": 1769613675167,
          "createAt": 1769613666557
        }
      },
      "IubxvL72QpTKHvJO3S2_R": {
        "id": "IubxvL72QpTKHvJO3S2_R",
        "tableId": "ZZqHZvyPEOG31dM5HyoMZ",
        "name": "",
        "comment": "",
        "dataType": "",
        "default": "",
        "options": 0,
        "ui": {
          "keys": 0,
          "widthName": 60,
          "widthComment": 60,
          "widthDataType": 60,
          "widthDefault": 60
        },
        "meta": {
          "updateAt": 1769613680242,
          "createAt": 1769613680242
        }
      },
      "dOK5IR4l7BOorgsXMyC3s": {
        "id": "dOK5IR4l7BOorgsXMyC3s",
        "tableId": "ZZqHZvyPEOG31dM5HyoMZ",
        "name": "user_id",
        "comment": "FK",
        "dataType": "BIGINT",
        "default": "",
        "options": 8,
        "ui": {
          "keys": 2,
          "widthName": 60,
          "widthComment": 60,
          "widthDataType": 60,
          "widthDefault": 60
        },
        "meta": {
          "updateAt": 1769613703337,
          "createAt": 1769613687372
        }
      },
      "szv4b63xO4XliXWOctoEy": {
        "id": "szv4b63xO4XliXWOctoEy",
        "tableId": "ZZqHZvyPEOG31dM5HyoMZ",
        "name": "pack_id",
        "comment": "FK",
        "dataType": "BIGINT",
        "default": "",
        "options": 8,
        "ui": {
          "keys": 2,
          "widthName": 60,
          "widthComment": 60,
          "widthDataType": 60,
          "widthDefault": 60
        },
        "meta": {
          "updateAt": 1769613709345,
          "createAt": 1769613695136
        }
      },
      "LaJSQkeRHvz3EGve0cCKN": {
        "id": "LaJSQkeRHvz3EGve0cCKN",
        "tableId": "PDSBscIUbI3lLRWMvjKsV",
        "name": "user_id",
        "comment": "FK",
        "dataType": "BIGINT",
        "default": "",
        "options": 8,
        "ui": {
          "keys": 2,
          "widthName": 60,
          "widthComment": 60,
          "widthDataType": 60,
          "widthDefault": 60
        },
        "meta": {
          "updateAt": 1769613741240,
          "createAt": 1769613720180
        }
      },
      "4mGqpgDMSU2-eGJE3JXek": {
        "id": "4mGqpgDMSU2-eGJE3JXek",
        "tableId": "PDSBscIUbI3lLRWMvjKsV",
        "name": "item_id",
        "comment": "FK",
        "dataType": "BIGINT",
        "default": "",
        "options": 8,
        "ui": {
          "keys": 2,
          "widthName": 60,
          "widthComment": 60,
          "widthDataType": 60,
          "widthDefault": 60
        },
        "meta": {
          "updateAt": 1769613738345,
          "createAt": 1769613731389
        }
      },
      "PZIhkKWR3s2Ys-lAC7NAr": {
        "id": "PZIhkKWR3s2Ys-lAC7NAr",
        "tableId": "DsMm1UbPEc01xHb0e5kDp",
        "name": "detail",
        "comment": "카테고리 세부 사항",
        "dataType": "VARCHAR(50)",
        "default": "",
        "options": 8,
        "ui": {
          "keys": 0,
          "widthName": 60,
          "widthComment": 92,
          "widthDataType": 83,
          "widthDefault": 60
        },
        "meta": {
          "updateAt": 1769744464191,
          "createAt": 1769744260247
        }
      },
      "wPhAZPRRzNTTLn5Gr7CNt": {
        "id": "wPhAZPRRzNTTLn5Gr7CNt",
        "tableId": "DsMm1UbPEc01xHb0e5kDp",
        "name": "",
        "comment": "",
        "dataType": "",
        "default": "",
        "options": 0,
        "ui": {
          "keys": 0,
          "widthName": 60,
          "widthComment": 60,
          "widthDataType": 60,
          "widthDefault": 60
        },
        "meta": {
          "updateAt": 1769744443517,
          "createAt": 1769744443517
        }
      },
      "toy7Kr3_W9WcaPYxsHChV": {
        "id": "toy7Kr3_W9WcaPYxsHChV",
        "tableId": "3APtNOasTm-e0OA6a9FNY",
        "name": "detail",
        "comment": "카테고리 세부 사항",
        "dataType": "VARCHAR(50)",
        "default": "",
        "options": 8,
        "ui": {
          "keys": 0,
          "widthName": 60,
          "widthComment": 92,
          "widthDataType": 83,
          "widthDefault": 60
        },
        "meta": {
          "updateAt": 1769744494812,
          "createAt": 1769744456884
        }
      },
      "Jg9GfYS1ed0Xp9u9lhhoT": {
        "id": "Jg9GfYS1ed0Xp9u9lhhoT",
        "tableId": "cBh8ORWDjyegNE57Iuv2o",
        "name": "interest_id",
        "comment": "FK",
        "dataType": "BIGINT",
        "default": "",
        "options": 8,
        "ui": {
          "keys": 2,
          "widthName": 62,
          "widthComment": 60,
          "widthDataType": 60,
          "widthDefault": 60
        },
        "meta": {
          "updateAt": 1769744547487,
          "createAt": 1769744523648
        }
      },
      "cJr6u7X83snnYU136IQS1": {
        "id": "cJr6u7X83snnYU136IQS1",
        "tableId": "cBh8ORWDjyegNE57Iuv2o",
        "name": "situation_id",
        "comment": "FK",
        "dataType": "BIGINT",
        "default": "",
        "options": 8,
        "ui": {
          "keys": 2,
          "widthName": 68,
          "widthComment": 60,
          "widthDataType": 60,
          "widthDefault": 60
        },
        "meta": {
          "updateAt": 1769744592707,
          "createAt": 1769744576987
        }
      }
    },
    "relationshipEntities": {
      "QtRMVYtBxuDPORMh0mBdp": {
        "id": "QtRMVYtBxuDPORMh0mBdp",
        "identification": false,
        "relationshipType": 16,
        "startRelationshipType": 2,
        "start": {
          "tableId": "bJ7AOC6b5UBri3XKxWYJY",
          "columnIds": [
            "Y5sg76HQD1b4WUYJJ4V9G"
          ],
          "x": 540.9894,
          "y": 475.5131,
          "direction": 2
        },
        "end": {
          "tableId": "t-nhS9VuC9Mb4hcV-9Yt2",
          "columnIds": [
            "zc6g-Z520uRGElgQm_DuH"
          ],
          "x": 679.3185,
          "y": 482.5019,
          "direction": 1
        },
        "meta": {
          "updateAt": 1769513371899,
          "createAt": 1769513371899
        }
      },
      "SriMF4zE240RWndT0irJG": {
        "id": "SriMF4zE240RWndT0irJG",
        "identification": false,
        "relationshipType": 16,
        "startRelationshipType": 2,
        "start": {
          "tableId": "DsMm1UbPEc01xHb0e5kDp",
          "columnIds": [
            "ZGvFOIXwQ1aP1SQKQ4I5i"
          ],
          "x": 1536.7253,
          "y": 468.2867,
          "direction": 1
        },
        "end": {
          "tableId": "t-nhS9VuC9Mb4hcV-9Yt2",
          "columnIds": [
            "uitMLZ80N_hGuoxqW-LEX"
          ],
          "x": 1108.3184999999999,
          "y": 482.5019,
          "direction": 2
        },
        "meta": {
          "updateAt": 1769513401131,
          "createAt": 1769513401131
        }
      },
      "CYkOLGQC2RjCafAVkzS74": {
        "id": "CYkOLGQC2RjCafAVkzS74",
        "identification": false,
        "relationshipType": 16,
        "startRelationshipType": 2,
        "start": {
          "tableId": "bJ7AOC6b5UBri3XKxWYJY",
          "columnIds": [
            "Y5sg76HQD1b4WUYJJ4V9G"
          ],
          "x": 540.9894,
          "y": 413.5131,
          "direction": 2
        },
        "end": {
          "tableId": "_B8cZ5qmp5gvIdren79eJ",
          "columnIds": [
            "jgbj5Ow5Oi__-xi8rXagR"
          ],
          "x": 677.6251,
          "y": 271.7419,
          "direction": 1
        },
        "meta": {
          "updateAt": 1769513517527,
          "createAt": 1769513517527
        }
      },
      "vk1vQvEWh4J0BeYfNwOv1": {
        "id": "vk1vQvEWh4J0BeYfNwOv1",
        "identification": false,
        "relationshipType": 16,
        "startRelationshipType": 2,
        "start": {
          "tableId": "3APtNOasTm-e0OA6a9FNY",
          "columnIds": [
            "Yik8C7n_4LANoofIXLQeJ"
          ],
          "x": 1489.5813,
          "y": 250.9683,
          "direction": 1
        },
        "end": {
          "tableId": "_B8cZ5qmp5gvIdren79eJ",
          "columnIds": [
            "dBb5AGYLM8jVGJeQwkprV"
          ],
          "x": 1100.6251,
          "y": 271.7419,
          "direction": 2
        },
        "meta": {
          "updateAt": 1769513533078,
          "createAt": 1769513533078
        }
      },
      "oytHm6IvmnoRFCmT0WDdU": {
        "id": "oytHm6IvmnoRFCmT0WDdU",
        "identification": false,
        "relationshipType": 16,
        "startRelationshipType": 2,
        "start": {
          "tableId": "3APtNOasTm-e0OA6a9FNY",
          "columnIds": [
            "Yik8C7n_4LANoofIXLQeJ"
          ],
          "x": 1488.867,
          "y": 350.53970000000004,
          "direction": 8
        },
        "end": {
          "tableId": "qGNzk1VxwkfSKRvH8KQ8O",
          "columnIds": [
            "6fqObkZvz22PfHUOndUjb"
          ],
          "x": 1531.591,
          "y": 841.5057,
          "direction": 1
        },
        "meta": {
          "updateAt": 1769514618641,
          "createAt": 1769514618641
        }
      },
      "NpHYaO6jU_IuIanZbPdJE": {
        "id": "NpHYaO6jU_IuIanZbPdJE",
        "identification": false,
        "relationshipType": 16,
        "startRelationshipType": 2,
        "start": {
          "tableId": "DsMm1UbPEc01xHb0e5kDp",
          "columnIds": [
            "ZGvFOIXwQ1aP1SQKQ4I5i"
          ],
          "x": 1490.9657,
          "y": 556.9426000000001,
          "direction": 8
        },
        "end": {
          "tableId": "YqpgNdCUwXpWWFYMZkHj0",
          "columnIds": [
            "bP5dLdS8N3D_0oczoMX8e"
          ],
          "x": 1485.3098,
          "y": 645.2561,
          "direction": 4
        },
        "meta": {
          "updateAt": 1769514713298,
          "createAt": 1769514713298
        }
      },
      "G7h1ObFI-S6KhWcTX7jS-": {
        "id": "G7h1ObFI-S6KhWcTX7jS-",
        "identification": false,
        "relationshipType": 16,
        "startRelationshipType": 2,
        "start": {
          "tableId": "bJ7AOC6b5UBri3XKxWYJY",
          "columnIds": [
            "Y5sg76HQD1b4WUYJJ4V9G"
          ],
          "x": 540.9894,
          "y": 537.5131,
          "direction": 2
        },
        "end": {
          "tableId": "cBh8ORWDjyegNE57Iuv2o",
          "columnIds": [
            "Lf-H19PaEikcDbGd-xXV4"
          ],
          "x": 1002.5852,
          "y": 655.0625,
          "direction": 1
        },
        "meta": {
          "updateAt": 1769514843010,
          "createAt": 1769514843010
        }
      },
      "--daGe-uRkCeGj0nYv66x": {
        "id": "--daGe-uRkCeGj0nYv66x",
        "identification": false,
        "relationshipType": 16,
        "startRelationshipType": 2,
        "start": {
          "tableId": "YqpgNdCUwXpWWFYMZkHj0",
          "columnIds": [
            "Ictq5yX_96r7zLmYbT9MC"
          ],
          "x": 1255.8098,
          "y": 709.2561,
          "direction": 1
        },
        "end": {
          "tableId": "cBh8ORWDjyegNE57Iuv2o",
          "columnIds": [
            "KxA9qeagDOFxgyEA_Ma6i"
          ],
          "x": 1218.5852,
          "y": 850.4991,
          "direction": 4
        },
        "meta": {
          "updateAt": 1769514920021,
          "createAt": 1769514920021
        }
      },
      "BtnZY4_Jfe0KJNuz1Eno1": {
        "id": "BtnZY4_Jfe0KJNuz1Eno1",
        "identification": false,
        "relationshipType": 16,
        "startRelationshipType": 2,
        "start": {
          "tableId": "qGNzk1VxwkfSKRvH8KQ8O",
          "columnIds": [
            "nqZpfXMdmHOsL6RbUUM2f"
          ],
          "x": 1531.591,
          "y": 905.5057,
          "direction": 1
        },
        "end": {
          "tableId": "cBh8ORWDjyegNE57Iuv2o",
          "columnIds": [
            "TEr5ElEuN_yR4rXy7aTg4"
          ],
          "x": 1434.5852,
          "y": 950.4991,
          "direction": 2
        },
        "meta": {
          "updateAt": 1769514977445,
          "createAt": 1769514977445
        }
      },
      "MiSyxptPR04zAPTrbKlOz": {
        "id": "MiSyxptPR04zAPTrbKlOz",
        "identification": false,
        "relationshipType": 16,
        "startRelationshipType": 2,
        "start": {
          "tableId": "cBh8ORWDjyegNE57Iuv2o",
          "columnIds": [
            "SecDLSP7hc7TMIxoGvMON"
          ],
          "x": 639.1739,
          "y": 891.7915666666665,
          "direction": 2
        },
        "end": {
          "tableId": "9Ran1wBWSEnygQOVVznXd",
          "columnIds": [
            "2w5ryMWNqG2Eqg6gJwZN9"
          ],
          "x": 805.137,
          "y": 1042.0347000000002,
          "direction": 1
        },
        "meta": {
          "updateAt": 1769516437876,
          "createAt": 1769516437876
        }
      },
      "5sax-KS1xd-r-UnyF2Dx_": {
        "id": "5sax-KS1xd-r-UnyF2Dx_",
        "identification": false,
        "relationshipType": 16,
        "startRelationshipType": 2,
        "start": {
          "tableId": "bJ7AOC6b5UBri3XKxWYJY",
          "columnIds": [
            "Y5sg76HQD1b4WUYJJ4V9G"
          ],
          "x": 419.7394,
          "y": 606.5131,
          "direction": 8
        },
        "end": {
          "tableId": "sl59DqkQiHdpea1EMLv-R",
          "columnIds": [
            "gDyQXFINDlNAEr80PoSbc"
          ],
          "x": 293.5,
          "y": 1384.7094,
          "direction": 4
        },
        "meta": {
          "updateAt": 1769571619489,
          "createAt": 1769571619489
        }
      },
      "gWU06k4oyCHZ-Rpixvm8g": {
        "id": "gWU06k4oyCHZ-Rpixvm8g",
        "identification": false,
        "relationshipType": 16,
        "startRelationshipType": 2,
        "start": {
          "tableId": "sl59DqkQiHdpea1EMLv-R",
          "columnIds": [
            "gObAQtNx1fP_irqgB37Ot"
          ],
          "x": 197.25,
          "y": 1473.4594,
          "direction": 4
        },
        "end": {
          "tableId": "pHxvDRevJXyNO9omgJdtS",
          "columnIds": [
            "VbKbxZ9omYaOjAilnwVHT"
          ],
          "x": 198.25,
          "y": 1336.8315,
          "direction": 8
        },
        "meta": {
          "updateAt": 1769571664015,
          "createAt": 1769571664015
        }
      },
      "XNxtgQ3rgOa9Ae9Syk3h0": {
        "id": "XNxtgQ3rgOa9Ae9Syk3h0",
        "identification": false,
        "relationshipType": 16,
        "startRelationshipType": 2,
        "start": {
          "tableId": "bJ7AOC6b5UBri3XKxWYJY",
          "columnIds": [
            "Y5sg76HQD1b4WUYJJ4V9G"
          ],
          "x": 161.4894,
          "y": 630.5131,
          "direction": 8
        },
        "end": {
          "tableId": "pHxvDRevJXyNO9omgJdtS",
          "columnIds": [
            "hqTIp10iZnrDULrJjJfog"
          ],
          "x": 198.25,
          "y": 1160.8315,
          "direction": 4
        },
        "meta": {
          "updateAt": 1769571692649,
          "createAt": 1769571692649
        }
      },
      "yzRRJ6yZITA_lt7BBymsy": {
        "id": "yzRRJ6yZITA_lt7BBymsy",
        "identification": false,
        "relationshipType": 16,
        "startRelationshipType": 2,
        "start": {
          "tableId": "cBh8ORWDjyegNE57Iuv2o",
          "columnIds": [
            "SecDLSP7hc7TMIxoGvMON"
          ],
          "x": 1199.5852,
          "y": 787.0625,
          "direction": 8
        },
        "end": {
          "tableId": "CKd0J5jyyS6BkdxLBP2mH",
          "columnIds": [
            "kQjK_Z7n8C6qBnbFBpgHY"
          ],
          "x": 1045.6494,
          "y": 1010.3384,
          "direction": 4
        },
        "meta": {
          "updateAt": 1769613327996,
          "createAt": 1769613327996
        }
      },
      "TEWzEHRSevKxakZu3lXj1": {
        "id": "TEWzEHRSevKxakZu3lXj1",
        "identification": false,
        "relationshipType": 16,
        "startRelationshipType": 2,
        "start": {
          "tableId": "CKd0J5jyyS6BkdxLBP2mH",
          "columnIds": [
            "Cg6PtHxSkBoKMiCshonY-"
          ],
          "x": 1255.6494,
          "y": 1134.3384,
          "direction": 2
        },
        "end": {
          "tableId": "9Ran1wBWSEnygQOVVznXd",
          "columnIds": [
            "3bjIvqWdn__100c0zx3xo"
          ],
          "x": 1406.9609,
          "y": 1104.6019,
          "direction": 1
        },
        "meta": {
          "updateAt": 1769613371851,
          "createAt": 1769613371851
        }
      },
      "j0ZsCNqoafOo1I4ldlHFG": {
        "id": "j0ZsCNqoafOo1I4ldlHFG",
        "identification": false,
        "relationshipType": 16,
        "startRelationshipType": 2,
        "start": {
          "tableId": "bJ7AOC6b5UBri3XKxWYJY",
          "columnIds": [
            "Y5sg76HQD1b4WUYJJ4V9G"
          ],
          "x": 540.9894,
          "y": 599.5131,
          "direction": 2
        },
        "end": {
          "tableId": "ZZqHZvyPEOG31dM5HyoMZ",
          "columnIds": [
            "dOK5IR4l7BOorgsXMyC3s"
          ],
          "x": 715.8005,
          "y": 749.2237,
          "direction": 4
        },
        "meta": {
          "updateAt": 1769613687372,
          "createAt": 1769613687372
        }
      },
      "X2ZX_2ydFjT7ZdCCEqSSm": {
        "id": "X2ZX_2ydFjT7ZdCCEqSSm",
        "identification": false,
        "relationshipType": 16,
        "startRelationshipType": 2,
        "start": {
          "tableId": "cBh8ORWDjyegNE57Iuv2o",
          "columnIds": [
            "SecDLSP7hc7TMIxoGvMON"
          ],
          "x": 1002.5852,
          "y": 743.0625,
          "direction": 1
        },
        "end": {
          "tableId": "ZZqHZvyPEOG31dM5HyoMZ",
          "columnIds": [
            "szv4b63xO4XliXWOctoEy"
          ],
          "x": 898.3005,
          "y": 813.2237,
          "direction": 2
        },
        "meta": {
          "updateAt": 1769613695136,
          "createAt": 1769613695136
        }
      },
      "mRfRmX0y4MMhjZHM5yUmO": {
        "id": "mRfRmX0y4MMhjZHM5yUmO",
        "identification": false,
        "relationshipType": 16,
        "startRelationshipType": 2,
        "start": {
          "tableId": "bJ7AOC6b5UBri3XKxWYJY",
          "columnIds": [
            "Y5sg76HQD1b4WUYJJ4V9G"
          ],
          "x": 414.4894,
          "y": 630.5131,
          "direction": 8
        },
        "end": {
          "tableId": "PDSBscIUbI3lLRWMvjKsV",
          "columnIds": [
            "LaJSQkeRHvz3EGve0cCKN"
          ],
          "x": 423.872,
          "y": 918.1721,
          "direction": 4
        },
        "meta": {
          "updateAt": 1769613720181,
          "createAt": 1769613720181
        }
      },
      "LAwlFOnKcF9LL3AMzW0e2": {
        "id": "LAwlFOnKcF9LL3AMzW0e2",
        "identification": false,
        "relationshipType": 16,
        "startRelationshipType": 2,
        "start": {
          "tableId": "CKd0J5jyyS6BkdxLBP2mH",
          "columnIds": [
            "Cg6PtHxSkBoKMiCshonY-"
          ],
          "x": 835.6494,
          "y": 1134.3384,
          "direction": 1
        },
        "end": {
          "tableId": "PDSBscIUbI3lLRWMvjKsV",
          "columnIds": [
            "4mGqpgDMSU2-eGJE3JXek"
          ],
          "x": 606.3720000000001,
          "y": 982.1721,
          "direction": 2
        },
        "meta": {
          "updateAt": 1769613731389,
          "createAt": 1769613731389
        }
      },
      "bMC1SpSxdfX8ZeNoEsXoZ": {
        "id": "bMC1SpSxdfX8ZeNoEsXoZ",
        "identification": false,
        "relationshipType": 16,
        "startRelationshipType": 2,
        "start": {
          "tableId": "3APtNOasTm-e0OA6a9FNY",
          "columnIds": [
            "Yik8C7n_4LANoofIXLQeJ"
          ],
          "x": 1489.5813,
          "y": 314.9683,
          "direction": 1
        },
        "end": {
          "tableId": "cBh8ORWDjyegNE57Iuv2o",
          "columnIds": [
            "Jg9GfYS1ed0Xp9u9lhhoT"
          ],
          "x": 1396.5852,
          "y": 655.0625,
          "direction": 2
        },
        "meta": {
          "updateAt": 1769744523648,
          "createAt": 1769744523648
        }
      },
      "dCVsjZpSGvLLULXUjSTJC": {
        "id": "dCVsjZpSGvLLULXUjSTJC",
        "identification": false,
        "relationshipType": 16,
        "startRelationshipType": 2,
        "start": {
          "tableId": "DsMm1UbPEc01xHb0e5kDp",
          "columnIds": [
            "ZGvFOIXwQ1aP1SQKQ4I5i"
          ],
          "x": 1536.7253,
          "y": 532.2867,
          "direction": 1
        },
        "end": {
          "tableId": "cBh8ORWDjyegNE57Iuv2o",
          "columnIds": [
            "cJr6u7X83snnYU136IQS1"
          ],
          "x": 1396.5852,
          "y": 743.0625,
          "direction": 2
        },
        "meta": {
          "updateAt": 1769744576987,
          "createAt": 1769744576987
        }
      }
    },
    "indexEntities": {
      "na_XlrGLWOGN3dNRrJQzz": {
        "id": "na_XlrGLWOGN3dNRrJQzz",
        "name": "NICK_IDX",
        "tableId": "bJ7AOC6b5UBri3XKxWYJY",
        "indexColumnIds": [
          "CTw9v0IOEe-pFOoLzbv8k"
        ],
        "seqIndexColumnIds": [
          "CTw9v0IOEe-pFOoLzbv8k"
        ],
        "unique": false,
        "meta": {
          "updateAt": 1769509091442,
          "createAt": 1769509073205
        }
      }
    },
    "indexColumnEntities": {
      "CTw9v0IOEe-pFOoLzbv8k": {
        "id": "CTw9v0IOEe-pFOoLzbv8k",
        "indexId": "na_XlrGLWOGN3dNRrJQzz",
        "columnId": "ZYNf3lizgpnCOehkqkNnV",
        "orderType": 1,
        "meta": {
          "updateAt": 1769509091442,
          "createAt": 1769509091442
        }
      }
    },
    "memoEntities": {
      "2LAcKljObBZY5iIZKcr4a": {
        "id": "2LAcKljObBZY5iIZKcr4a",
        "value": "취향 카테고리\n순간 카테고리\n이 2개는 별개의 테이블 생성 후, users 테이블과 M:N 연관관계 맺음",
        "ui": {
          "x": 34.823,
          "y": 28.0435,
          "zIndex": 44,
          "width": 116,
          "height": 100,
          "color": ""
        },
        "meta": {
          "updateAt": 1769571095503,
          "createAt": 1769510690078
        }
      },
      "Bl6KcNpFmT3_BBgmrssNI": {
        "id": "Bl6KcNpFmT3_BBgmrssNI",
        "value": "items 테이블 생성 필요\n(아직 서비스 제공 아이템명과 사용자 정의 아이템명 기준 정리 필요)",
        "ui": {
          "x": 3.3392,
          "y": 944.2955,
          "zIndex": 318,
          "width": 116,
          "height": 100,
          "color": ""
        },
        "meta": {
          "updateAt": 1769570827636,
          "createAt": 1769516052347
        }
      },
      "9xNAZAvfZx1XCnUfsoWPo": {
        "id": "9xNAZAvfZx1XCnUfsoWPo",
        "value": "[erd 내 명칭] = [와이어프레임 내 명칭]\n\n사용자 취향 카테고리 = 라이프 스타일\n\n사용자 순간 카테고리 = 관심 상황\n\n",
        "ui": {
          "x": 674,
          "y": 51,
          "zIndex": 422,
          "width": 333,
          "height": 100,
          "color": ""
        },
        "meta": {
          "updateAt": 1769570451361,
          "createAt": 1769570327325
        }
      },
      "tsO7A6ZhrKp7ukdtr2z-e": {
        "id": "tsO7A6ZhrKp7ukdtr2z-e",
        "value": "3일 연속 방문 등의 횟수 세기는 rdbms보다는 nosql에서 관리하는 것이 나아보임\n\n",
        "ui": {
          "x": 433.75,
          "y": 1474.5815,
          "zIndex": 667,
          "width": 215,
          "height": 100,
          "color": ""
        },
        "meta": {
          "updateAt": 1769571771577,
          "createAt": 1769571514838
        }
      },
      "KCkfC8SPr6upozfYdxDF8": {
        "id": "KCkfC8SPr6upozfYdxDF8",
        "value": "사용자 이메일 누락 보완\n사용자 직군은 WF 상에서 태그 선택형으로 기능 제공 중이라 ENUM 채택",
        "ui": {
          "x": 38.9985,
          "y": 233.0755,
          "zIndex": 687,
          "width": 116,
          "height": 100,
          "color": ""
        },
        "meta": {
          "updateAt": 1769594014428,
          "createAt": 1769593987660
        }
      }
    }
  }
}